pydnspod/__init__.py
pydnspod/config.py
pydnspod/pydnspod.py
pydnspod2-0.1.0.dist-info/METADATA
pydnspod2-0.1.0.dist-info/WHEEL
pydnspod2-0.1.0.dist-info/top_level.txt
pydnspod2-0.1.0.dist-info/RECORD
