Metadata-Version: 2.1
Name: pydnspod2
Version: 0.1.0
Summary: pydnspod - a dnspod api sdk
Home-page: https://github.com/tclh123/pydnspod
Author: solos
Author-email: lxl1217@gmail.com
Maintainer: Harry Lee
Maintainer-email: tclh123@gmail.com
License: MIT License
Keywords: DNSPod,DNS,SDK
Platform: any
Classifier: Programming Language :: Python
Classifier: Programming Language :: Python :: 2.7
Classifier: Programming Language :: Python :: 3
Classifier: Programming Language :: Python :: 3.4
Classifier: Programming Language :: Python :: 3.5
Classifier: Programming Language :: Python :: 3.6
Classifier: Programming Language :: Python :: 3.7
Classifier: Development Status :: 5 - Production/Stable
Classifier: Environment :: Console
Classifier: Intended Audience :: Developers
Classifier: License :: OSI Approved :: MIT License
Classifier: Operating System :: POSIX :: Linux
Classifier: Topic :: Software Development :: Libraries :: Python Modules
Requires-Dist: six
